[
    {
        "index": 1,
        "shop": "餃子園手作水餃",
        "category": [
            "糕餅"
        ],
        "zone": "桃竹苗",
        "city": "桃園市",
        "area": "大園區",
        "market_address": "桃園市大園區大園里忠孝三街１９號",
        "pay_list": [
            "台灣pay",
            "信用卡"
        ]
    },
    {
        "index": 2,
        "shop": "鄉夏甜室",
        "category": [
            "糕餅"
        ],
        "zone": "桃竹苗",
        "city": "桃園市",
        "area": "大園區",
        "market_address": "桃園市大園區埔心里００５鄰埔心街８２號",
        "pay_list": [
            "LINE Pay Money"
        ]
    },
    {
        "index": 3,
        "shop": "京喜堂",
        "category": [
            "糕餅"
        ],
        "zone": "桃竹苗",
        "city": "桃園市",
        "area": "大園區",
        "market_address": "桃園市大園區橫峰里領航北路四段５２號",
        "pay_list": [
            "台灣pay",
            "信用卡"
        ]
    },
    {
        "index": 4,
        "shop": "京彩貿易有限公司",
        "category": [
            "餐飲",
            "糕餅"
        ],
        "zone": "桃竹苗",
        "city": "桃園市",
        "area": "大園區",
        "market_address": "桃園市大園區菓林里０１５鄰崁下４９－３號",
        "pay_list": [
            "信用卡"
        ]
    },
    {
        "index": 5,
        "shop": "正優島企業行",
        "category": [
            "糕餅"
        ],
        "zone": "桃竹苗",
        "city": "桃園市",
        "area": "大園區",
        "market_address": "桃園市大園區田心里０１４鄰新興路１３２―６號１樓",
        "pay_list": [
            "台灣pay",
            "LINE Pay Money"
        ]
    }
]