{
  "Info": [
    {
      "IsSuccess": "True",
      "InAddress": "臺北市中正區東門市場新舘第２０號",
      "InSRS": "EPSG:4326",
      "InFuzzyType": "[單雙號機制]+[最近門牌號機制]",
      "InFuzzyBuffer": "0",
      "InIsOnlyFullMatch": "False",
      "InIsLockCounty": "True",
      "InIsLockTown": "False",
      "InIsLockVillage": "False",
      "InIsLockRoadSection": "False",
      "InIsLockLane": "False",
      "InIsLockAlley": "False",
      "InIsLockArea": "False",
      "InIsSameNumber_SubNumber": "True",
      "InCanIgnoreVillage": "True",
      "InCanIgnoreNeighborhood": "True",
      "InReturnMaxCount": "0",
      "OutTotal": "51",
      "OutMatchType": "模糊比對",
      "OutMatchCode": "[臺北市]\tT:1,V:-1,R:-1,S:-1,L:-1,A:-1,SA:-1,T:-1,AR:0,NO:1,E:-1,N:-1",
      "OutTraceInfo": "[臺北市]\t { 模糊比對 } (中正區)\t找到符合的[鄉鎮市區]，(東門市場新舘第)\t找不到符合的[地區]，轉換搜尋找不到符合的[地區]，(20號)\t找到符合的[門牌號碼]，進行[雙號過濾]，模糊比對找到 51 筆符合的門牌地址。( 限制回傳 10 筆門牌地址 )"
    }
  ],
  "AddressList": [
    {
      "FULL_ADDR": "臺北市中正區光復里6鄰武昌街一段20號",
      "COUNTY": "臺北市",
      "TOWN": "中正區",
      "VILLAGE": "光復里",
      "NEIGHBORHOOD": "6鄰",
      "ROAD": "武昌街",
      "SECTION": "1",
      "LANE": "",
      "ALLEY": "",
      "SUB_ALLEY": "",
      "TONG": "",
      "AREA": "",
      "NUMBER": "20號",
      "X": 121.512429,
      "Y": 25.044014
    },
    {
      "FULL_ADDR": "臺北市中正區梅花里11鄰杭州北路20號",
      "COUNTY": "臺北市",
      "TOWN": "中正區",
      "VILLAGE": "梅花里",
      "NEIGHBORHOOD": "11鄰",
      "ROAD": "杭州北路",
      "SECTION": "",
      "LANE": "",
      "ALLEY": "",
      "SUB_ALLEY": "",
      "TONG": "",
      "AREA": "",
      "NUMBER": "20號",
      "X": 121.526886,
      "Y": 25.044551
    },
    {
      "FULL_ADDR": "臺北市中正區螢圃里22鄰厦門街20號",
      "COUNTY": "臺北市",
      "TOWN": "中正區",
      "VILLAGE": "螢圃里",
      "NEIGHBORHOOD": "22鄰",
      "ROAD": "厦門街",
      "SECTION": "",
      "LANE": "",
      "ALLEY": "",
      "SUB_ALLEY": "",
      "TONG": "",
      "AREA": "",
      "NUMBER": "20號",
      "X": 121.517690,
      "Y": 25.026206
    },
    {
      "FULL_ADDR": "臺北市中正區南福里24鄰寧波西街20號",
      "COUNTY": "臺北市",
      "TOWN": "中正區",
      "VILLAGE": "南福里",
      "NEIGHBORHOOD": "24鄰",
      "ROAD": "寧波西街",
      "SECTION": "",
      "LANE": "",
      "ALLEY": "",
      "SUB_ALLEY": "",
      "TONG": "",
      "AREA": "",
      "NUMBER": "20號",
      "X": 121.518418,
      "Y": 25.031120
    },
    {
      "FULL_ADDR": "臺北市中正區新營里16鄰潮州街20號",
      "COUNTY": "臺北市",
      "TOWN": "中正區",
      "VILLAGE": "新營里",
      "NEIGHBORHOOD": "16鄰",
      "ROAD": "潮州街",
      "SECTION": "",
      "LANE": "",
      "ALLEY": "",
      "SUB_ALLEY": "",
      "TONG": "",
      "AREA": "",
      "NUMBER": "20號",
      "X": 121.521627,
      "Y": 25.029484
    },
    {
      "FULL_ADDR": "臺北市中正區新營里21鄰金華街20號",
      "COUNTY": "臺北市",
      "TOWN": "中正區",
      "VILLAGE": "新營里",
      "NEIGHBORHOOD": "21鄰",
      "ROAD": "金華街",
      "SECTION": "",
      "LANE": "",
      "ALLEY": "",
      "SUB_ALLEY": "",
      "TONG": "",
      "AREA": "",
      "NUMBER": "20號",
      "X": 121.520414,
      "Y": 25.031656
    },
    {
      "FULL_ADDR": "臺北市中正區廈安里8鄰西藏路20號",
      "COUNTY": "臺北市",
      "TOWN": "中正區",
      "VILLAGE": "廈安里",
      "NEIGHBORHOOD": "8鄰",
      "ROAD": "西藏路",
      "SECTION": "",
      "LANE": "",
      "ALLEY": "",
      "SUB_ALLEY": "",
      "TONG": "",
      "AREA": "",
      "NUMBER": "20號",
      "X": 121.507341,
      "Y": 25.030781
    },
    {
      "FULL_ADDR": "臺北市中正區文盛里9鄰羅斯福路四段20號",
      "COUNTY": "臺北市",
      "TOWN": "中正區",
      "VILLAGE": "文盛里",
      "NEIGHBORHOOD": "9鄰",
      "ROAD": "羅斯福路",
      "SECTION": "4",
      "LANE": "",
      "ALLEY": "",
      "SUB_ALLEY": "",
      "TONG": "",
      "AREA": "",
      "NUMBER": "20號",
      "X": 121.533052,
      "Y": 25.015687
    },
    {
      "FULL_ADDR": "臺北市中正區黎明里12鄰許昌街20號",
      "COUNTY": "臺北市",
      "TOWN": "中正區",
      "VILLAGE": "黎明里",
      "NEIGHBORHOOD": "12鄰",
      "ROAD": "許昌街",
      "SECTION": "",
      "LANE": "",
      "ALLEY": "",
      "SUB_ALLEY": "",
      "TONG": "",
      "AREA": "",
      "NUMBER": "20號",
      "X": 121.516600,
      "Y": 25.045442
    },
    {
      "FULL_ADDR": "臺北市中正區黎明里1鄰中山北路一段20號",
      "COUNTY": "臺北市",
      "TOWN": "中正區",
      "VILLAGE": "黎明里",
      "NEIGHBORHOOD": "1鄰",
      "ROAD": "中山北路",
      "SECTION": "1",
      "LANE": "",
      "ALLEY": "",
      "SUB_ALLEY": "",
      "TONG": "",
      "AREA": "",
      "NUMBER": "20號",
      "X": 121.519802,
      "Y": 25.046597
    }
  ]
}