[
    {
        "index": 1,
        "shop": "達卡兒咖啡坊",
        "category": [
            "餐飲"
        ],
        "zone": "台東",
        "city": "臺東縣",
        "area": "東河鄉",
        "market_address": "臺東縣東河鄉都蘭村新社３５號",
        "pay_list": [
            "台灣pay"
        ]
    },
    {
        "index": 2,
        "shop": "海人上菜館",
        "category": [
            "餐飲"
        ],
        "zone": "台東",
        "city": "臺東縣",
        "area": "東河鄉",
        "market_address": "臺東縣東河鄉都蘭村都蘭路４４５―５號",
        "pay_list": [
            "台灣pay"
        ]
    },
    {
        "index": 3,
        "shop": "眾群企業社",
        "category": [
            "餐飲"
        ],
        "zone": "台東",
        "city": "臺東縣",
        "area": "東河鄉",
        "market_address": "臺東縣東河鄉都蘭村都蘭路４５９―２號",
        "pay_list": [
            "信用卡"
        ]
    },
    {
        "index": 4,
        "shop": "國軍退除役官兵輔導委員會臺東農場東河休閒農莊",
        "category": [
            "餐飲"
        ],
        "zone": "台東",
        "city": "臺東縣",
        "area": "東河鄉",
        "market_address": "臺東縣東河鄉北源村德高老路６７號",
        "pay_list": [
            "信用卡"
        ]
    },
    {
        "index": 5,
        "shop": "洛恩米薩克咖啡坊",
        "category": [
            "餐飲"
        ],
        "zone": "台東",
        "city": "臺東縣",
        "area": "東河鄉",
        "market_address": "臺東縣東河鄉都蘭村都蘭路２７４―２號",
        "pay_list": [
            "信用卡"
        ]
    },
    {
        "index": 6,
        "shop": "熱帶低氣壓工作室",
        "category": [
            "餐飲"
        ],
        "zone": "台東",
        "city": "臺東縣",
        "area": "東河鄉",
        "market_address": "臺東縣東河鄉東河村００７鄰南東河路１０８號",
        "pay_list": [
            "信用卡",
            "LINE Pay Money"
        ]
    },
    {
        "index": 7,
        "shop": "海角航海有限公司",
        "category": [
            "餐飲"
        ],
        "zone": "台東",
        "city": "臺東縣",
        "area": "東河鄉",
        "market_address": "臺東縣東河鄉興昌村南八里１１－１０號",
        "pay_list": [
            "信用卡",
            "街口"
        ]
    },
    {
        "index": 8,
        "shop": "東舖興業社",
        "category": [
            "餐飲"
        ],
        "zone": "台東",
        "city": "臺東縣",
        "area": "東河鄉",
        "market_address": "臺東縣東河鄉都蘭村都蘭路１２１之１號",
        "pay_list": [
            "LINE Pay Money"
        ]
    },
    {
        "index": 9,
        "shop": "台拾壹藝術工作室",
        "category": [
            "餐飲"
        ],
        "zone": "台東",
        "city": "臺東縣",
        "area": "東河鄉",
        "market_address": "臺東縣東河鄉都蘭村都蘭６１號",
        "pay_list": [
            "信用卡"
        ]
    },
    {
        "index": 10,
        "shop": "星浪新蘭恩典企業社",
        "category": [
            "餐飲"
        ],
        "zone": "台東",
        "city": "臺東縣",
        "area": "東河鄉",
        "market_address": "臺東縣東河鄉都蘭村那界路１２―１號",
        "pay_list": [
            "LINE Pay Money"
        ]
    },
    {
        "index": 11,
        "shop": "鄭記食為天饌",
        "category": [
            "餐飲"
        ],
        "zone": "台東",
        "city": "臺東縣",
        "area": "東河鄉",
        "market_address": "臺東縣東河鄉都蘭村０２０鄰都蘭路８６號",
        "pay_list": [
            "台灣pay"
        ]
    },
    {
        "index": 12,
        "shop": "巴帝崮工作室",
        "category": [
            "餐飲"
        ],
        "zone": "台東",
        "city": "臺東縣",
        "area": "東河鄉",
        "market_address": "臺東縣東河鄉都蘭村都蘭２７４號",
        "pay_list": [
            "台灣pay"
        ]
    },
    {
        "index": 13,
        "shop": "女妖藝文工作室",
        "category": [
            "餐飲"
        ],
        "zone": "台東",
        "city": "臺東縣",
        "area": "東河鄉",
        "market_address": "臺東縣東河鄉都蘭村４６鄰都蘭路４２０―４號",
        "pay_list": [
            "信用卡"
        ]
    },
    {
        "index": 14,
        "shop": "我在玩工坊",
        "category": [
            "餐飲"
        ],
        "zone": "台東",
        "city": "臺東縣",
        "area": "東河鄉",
        "market_address": "臺東縣東河鄉隆昌村０１５鄰隆昌１８８號",
        "pay_list": [
            "信用卡"
        ]
    },
    {
        "index": 15,
        "shop": "台東衝浪店",
        "category": [
            "餐飲"
        ],
        "zone": "台東",
        "city": "臺東縣",
        "area": "東河鄉",
        "market_address": "臺東縣東河鄉東河村南東河路１８２號",
        "pay_list": [
            "台灣pay",
            "信用卡",
            "LINE Pay Money"
        ]
    },
    {
        "index": 16,
        "shop": "東河包子",
        "category": [
            "餐飲"
        ],
        "zone": "台東",
        "city": "臺東縣",
        "area": "東河鄉",
        "market_address": "臺東縣東河鄉東河村南東河路４２０號",
        "pay_list": [
            "街口"
        ]
    }
]